sedia_api_fetchers/EUFT_retrieve_facets.py
sedia_api_fetchers/EUFT_retrieve_faq.py
sedia_api_fetchers/EUFT_retrieve_funding_tenders.py
sedia_api_fetchers/EUFT_retrieve_participants.py
sedia_api_fetchers/EUFT_retrieve_projects.py
sedia_api_fetchers/EUFT_retrieve_topics.py
sedia_api_fetchers/__init__.py
sedia_api_fetchers/helpers/functions.py
sedia_api_fetchers-1.0.0.dist-info/licenses/LICENSE
sedia_api_fetchers-1.0.0.dist-info/METADATA
sedia_api_fetchers-1.0.0.dist-info/WHEEL
sedia_api_fetchers-1.0.0.dist-info/top_level.txt
sedia_api_fetchers-1.0.0.dist-info/RECORD
