Metadata-Version: 2.4
Name: sedia-api-fetchers
Version: 1.0.0
Summary: Python classes for fetching data from the European Commission's SEDIA API endpoints
Home-page: https://github.com/ajruben/sedia-api-fetchers
Author: Ruben Swarts
Author-email: Ruben Swarts <aj.rubenswarts@gmail.com>
License-Expression: MIT
Project-URL: Homepage, https://github.com/ajruben/sedia-api-fetchers
Project-URL: Repository, https://github.com/ajruben/sedia-api-fetchers
Project-URL: Issues, https://github.com/ajruben/sedia-api-fetchers/issues
Keywords: api,european-commission,sedia,data-fetching,research
Classifier: Development Status :: 4 - Beta
Classifier: Intended Audience :: Developers
Classifier: Intended Audience :: Science/Research
Classifier: Operating System :: OS Independent
Classifier: Programming Language :: Python :: 3
Classifier: Programming Language :: Python :: 3.8
Classifier: Programming Language :: Python :: 3.9
Classifier: Programming Language :: Python :: 3.10
Classifier: Programming Language :: Python :: 3.11
Classifier: Programming Language :: Python :: 3.12
Classifier: Topic :: Scientific/Engineering
Classifier: Topic :: Software Development :: Libraries :: Python Modules
Requires-Python: >=3.8
License-File: LICENSE
Requires-Dist: requests>=2.25.0
Requires-Dist: pandas>=1.3.0
Requires-Dist: numpy>=1.20.0
Requires-Dist: tqdm>=4.60.0
Requires-Dist: urllib3>=1.26.0
Provides-Extra: dev
Requires-Dist: pytest>=6.0; extra == "dev"
Requires-Dist: pytest-cov>=2.0; extra == "dev"
Requires-Dist: black>=21.0; extra == "dev"
Requires-Dist: flake8>=3.8; extra == "dev"
Requires-Dist: mypy>=0.800; extra == "dev"
Dynamic: author
Dynamic: home-page
Dynamic: license-file
Dynamic: requires-python
